apibean/pytest/__init__.py
apibean/pytest/cli.py
apibean/pytest/decorators.py
apibean/pytest/helpers.py
apibean/pytest/markers.py
apibean/pytest/plugin.py
apibean/pytest/renderers.py
apibean/pytest/settings.py
apibean/pytest/fixtures/__init__.py
apibean/pytest/fixtures/auth.py
apibean/pytest/fixtures/config.py
apibean/pytest/fixtures/container.py
apibean/pytest/fixtures/database.py
apibean/pytest/fixtures/seeds.py
apibean/pytest/hooks/seed_only.py
apibean/pytest/inspectors/__init__.py
apibean/pytest/inspectors/base.py
apibean/pytest/inspectors/container.py
apibean/pytest/inspectors/dbhandler.py
apibean/pytest/inspectors/fixtures.py
apibean/pytest/inspectors/seeders.py
apibean/pytest/protocols/__init__.py
apibean/pytest/protocols/config.py
apibean/pytest/protocols/container.py
apibean/pytest/protocols/database.py
apibean/pytest/protocols/util.py
apibean/pytest/wrappers/__init__.py
apibean/pytest/wrappers/container.py
pytest_apibean-0.1.0a3.dist-info/licenses/LICENSE.txt
pytest_apibean-0.1.0a3.dist-info/METADATA
pytest_apibean-0.1.0a3.dist-info/WHEEL
pytest_apibean-0.1.0a3.dist-info/entry_points.txt
pytest_apibean-0.1.0a3.dist-info/top_level.txt
pytest_apibean-0.1.0a3.dist-info/RECORD
