Metadata-Version: 2.4
Name: pytest-apibean
Version: 0.1.0a3
Summary: Pytest plugin providing apibean-based API testing fixtures integrated with apibean-client, designed for testing apibean REST services and datacore backends.
License-Expression: GPL-3.0
License-File: LICENSE.txt
Requires-Dist: anyio>=4.8.0
Requires-Dist: dependency-injector>=4.48.3
Requires-Dist: pytest
Provides-Extra: dev
Requires-Dist: nox; extra == "dev"
Dynamic: license-file
